wsntk/__init__.py
wsntk/network/__init__.py
wsntk/network/_link.py
wsntk/network/_network.py
wsntk/network/_sensor.py
wsntk/network/tests/__init__.py
wsntk/network/tests/test_link.py
wsntk/network/tests/test_network.py
wsntk/network/tests/test_node.py
wsntk/simulator/__init__.py
wsntk/simulator/_simulator.py
wsn_toolkit-0.0.5.dist-info/LICENSE.txt
wsn_toolkit-0.0.5.dist-info/METADATA
wsn_toolkit-0.0.5.dist-info/WHEEL
wsn_toolkit-0.0.5.dist-info/entry_points.txt
wsn_toolkit-0.0.5.dist-info/pbr.json
wsn_toolkit-0.0.5.dist-info/top_level.txt
wsn_toolkit-0.0.5.dist-info/RECORD
