Metadata-Version: 2.1
Name: wsn-toolkit
Version: 0.0.5
Summary: A toolkit for Wireless Sensor Networks.
Home-page: https://github.com/edielsonpf/wsn-toolkit
Author: Edielson P. Frigieri
Author-email: edielsonpf@gmail.com
License: MIT
Keywords: network, sensor, tools, simulation
Platform: UNKNOWN
Classifier: Development Status :: 4 - Beta
Classifier: Environment :: Console
Classifier: Intended Audience :: Science/Research
Classifier: Operating System :: MacOS :: MacOS X
Classifier: Operating System :: Microsoft :: Windows
Classifier: Operating System :: POSIX
Classifier: Programming Language :: Python :: 3 :: Only
Classifier: Programming Language :: Python :: 3.6
Classifier: Programming Language :: Python :: Implementation :: CPython
